windloadpy/__init__.py
windloadpy/module.py
windloadpy/mapping/__init__.py
windloadpy/mapping/location.py
windloadpy/solve/__init__.py
windloadpy/solve/gust_factor.py
windloadpy/solve/header.py
windloadpy/solve/natural_frequency.py
windloadpy/solve/signage.py
windloadpy/solve/velocity.py
windloadpy-0.1.1.dist-info/METADATA
windloadpy-0.1.1.dist-info/WHEEL
windloadpy-0.1.1.dist-info/top_level.txt
windloadpy-0.1.1.dist-info/RECORD
